<?xml version="1.0" encoding="utf-8"?><gmd:MD_Metadata xmlns:gmd="http://www.isotc211.org/2005/gmd" xmlns:gco="http://www.isotc211.org/2005/gco" xmlns:gml="http://www.opengis.net/gml" xmlns:xlink="http://www.w3.org/1999/xlink" xmlns:gmx="http://www.isotc211.org/2005/gmx">	<gmd:fileIdentifier>		<gco:CharacterString>ie.marine.data:dataset.2119</gco:CharacterString>	</gmd:fileIdentifier> <gmd:language><gmd:LanguageCode codeList=" http://www.loc.gov/standards/iso639-2/" codeListValue="eng">eng</gmd:LanguageCode></gmd:language>       <gmd:hierarchyLevel>               <gmd:MD_ScopeCode codeList="http://standards.iso.org/ittf/PubliclyAvailableStandards/ISO_19139_Schemas/resources/Codelist/gmxCodelists.xml#MD_ScopeCode" codeListValue="dataset">dataset</gmd:MD_ScopeCode>       </gmd:hierarchyLevel>	<gmd:contact>				<gmd:CI_ResponsibleParty>					<gmd:organisationName>						<gco:CharacterString>Marine Institute</gco:CharacterString>					</gmd:organisationName>					<gmd:contactInfo>						<gmd:CI_Contact>							<gmd:address>								<gmd:CI_Address>									<gmd:deliveryPoint>										<gco:CharacterString>Rinville</gco:CharacterString>									</gmd:deliveryPoint>									<gmd:city>										<gco:CharacterString>Oranmore</gco:CharacterString>									</gmd:city>									<gmd:administrativeArea>										<gco:CharacterString>Galway</gco:CharacterString>									</gmd:administrativeArea>									<gmd:postalCode>										<gco:CharacterString>H91 R673</gco:CharacterString>									</gmd:postalCode>									<gmd:country>										<gco:CharacterString>Ireland</gco:CharacterString>									</gmd:country>									<gmd:electronicMailAddress>										<gco:CharacterString>datarequests@marine.ie</gco:CharacterString>									</gmd:electronicMailAddress>								</gmd:CI_Address>							</gmd:address>						</gmd:CI_Contact>					</gmd:contactInfo>					<gmd:role>						<gmd:CI_RoleCode codeList="http://standards.iso.org/ittf/PubliclyAvailableStandards/ISO_19139_Schemas/resources/Codelist/gmxCodelists.xml#CI_RoleCode" codeListValue="pointOfContact">pointOfContact</gmd:CI_RoleCode>					</gmd:role>				</gmd:CI_ResponsibleParty>	</gmd:contact>       <gmd:dateStamp><gco:Date>2018-11-29</gco:Date></gmd:dateStamp>	<gmd:metadataStandardName>		<gco:CharacterString>ISDI Metadata Profile</gco:CharacterString>	</gmd:metadataStandardName>	<gmd:metadataStandardVersion>		<gco:CharacterString>1.2</gco:CharacterString>	</gmd:metadataStandardVersion>       <gmd:referenceSystemInfo>               <gmd:MD_ReferenceSystem>                       <gmd:referenceSystemIdentifier>                               <gmd:RS_Identifier>                                       <gmd:code>											<gco:CharacterString>http://www.opengis.net/def/crs/EPSG/0/3857</gco:CharacterString>										</gmd:code>										<gmd:codeSpace>											<gco:CharacterString>INSPIRE RS registry</gco:CharacterString>										</gmd:codeSpace>                               </gmd:RS_Identifier>                       </gmd:referenceSystemIdentifier>               </gmd:MD_ReferenceSystem>       </gmd:referenceSystemInfo>	<gmd:identificationInfo>		<gmd:MD_DataIdentification>			<gmd:citation>				<gmd:CI_Citation>					<gmd:title>						<gco:CharacterString>CV16039 Galway Bay Multidisciplinary Survey Planning Survey</gco:CharacterString>					</gmd:title>					<gmd:alternateTitle>						<gco:CharacterString>Galway Bay Multidisciplinary Survey Planning Survey</gco:CharacterString>					</gmd:alternateTitle>					<gmd:date>						<gmd:CI_Date>							<gmd:date>								<gco:Date>2018-01-25</gco:Date>							</gmd:date>							<gmd:dateType>								<gmd:CI_DateTypeCode codeList="http://standards.iso.org/ittf/PubliclyAvailableStandards/ISO_19139_Schemas/resources/Codelist/gmxCodelists.xml#CI_DateTypeCode" codeListValue="publication">publication</gmd:CI_DateTypeCode>							</gmd:dateType>						</gmd:CI_Date>					</gmd:date>					<gmd:date>						<gmd:CI_Date>							<gmd:date>								<gco:Date>2018-11-29</gco:Date>							</gmd:date>							<gmd:dateType>								<gmd:CI_DateTypeCode codeList="http://standards.iso.org/ittf/PubliclyAvailableStandards/ISO_19139_Schemas/resources/Codelist/gmxCodelists.xml#CI_DateTypeCode" codeListValue="revision">revision</gmd:CI_DateTypeCode>							</gmd:dateType>						</gmd:CI_Date>					</gmd:date>					<gmd:date>						<gmd:CI_Date>							<gmd:date>								<gco:Date>2016-10-22</gco:Date>							</gmd:date>							<gmd:dateType>								<gmd:CI_DateTypeCode codeList="http://standards.iso.org/ittf/PubliclyAvailableStandards/ISO_19139_Schemas/resources/Codelist/gmxCodelists.xml#CI_DateTypeCode" codeListValue="creation">creation</gmd:CI_DateTypeCode>							</gmd:dateType>						</gmd:CI_Date>					</gmd:date>					<gmd:identifier>						<gmd:RS_Identifier>							<gmd:code>								<gco:CharacterString>ie.marine.data:dataset.2119</gco:CharacterString>							</gmd:code>							<gmd:codeSpace>								<gco:CharacterString>https://data.marine.ie/</gco:CharacterString>							</gmd:codeSpace>						</gmd:RS_Identifier>					</gmd:identifier>					<gmd:identifier>						<gmd:RS_Identifier>							<gmd:code>								<gco:CharacterString>{&quot;@context&quot;:&quot;http://schema.org&quot;,&quot;@type&quot;:&quot;Dataset&quot;,&quot;name&quot;:&quot;CV16039 Galway Bay Multidisciplinary Survey Planning Survey&quot;,&quot;description&quot;:&quot;This cruise organised by Galway Mayo Institute of Technology (GMIT) was organised to use peer assisted learning to enable training of undergraduate degree students on the course in Applied Marine and Freshwater Biology in various fisheries, megafauna, benthic and oceanographic sampling methods at sea.  Those students who are on board a research vessel for a second or third time, whether undergraduate or postgraduate, will train (Peer Assisted Learning) students who are on board for the first time. This allows reinforcement of prior learning under the supervision of GMIT lecturers and postgrads. The aim is for the students to gain competencies in station position fixing, data logging, sampling and on-board sampling processing at sea. 

This cruise took place in October 2016 in Galway Bay on board the Marine Institute's R.V. Celtic Voyager.  Sampling and surveys conducted during the cruise include:
the use of box dredges, day grabs,  reineck box corer,  beam/otter trawl, plankton nets, CTD rosette, hydrophone and Remotely Operated Vehicles (ROV). 
 &quot;,&quot;url&quot;: &quot;https://data.marine.ie/dataset/2119&quot;,&quot;temporalCoverage&quot;: &quot;2016-10-22T23:00:00/2016-10-31&quot;,&quot;keywords&quot;:[&quot;Atmosphere&quot;,&quot;Meteorology&quot;],&quot;variablesMeasured&quot;:[&quot;Pressure (measured variable) exerted by the atmosphere&quot;,&quot;Temperature of the atmosphere&quot;,&quot;Date and time&quot;,&quot;Depth below surface of the water body&quot;,&quot;Latitude north&quot;,&quot;Longitude east&quot;,&quot;Platform Id&quot;,&quot;Platform Name&quot;,&quot;Orientation (horizontal relative to true north) of measurement device {heading}&quot;,&quot;Relative humidity of the atmosphere&quot;,&quot;Sea Surface Salinity&quot;,&quot;Sea Surface Temperature&quot;,&quot;Direction from of wind relative to True North {wind direction} in the atmosphere&quot;,&quot;Speed of wind {wind speed} in the atmosphere&quot;,&quot;Speed of wind (gust) {wind speed} in the atmosphere&quot;],&quot;creator&quot;:{&quot;@type&quot;:&quot;Organization&quot;,&quot;url&quot;:&quot;http://www.gmit.ie/&quot;,&quot;name&quot;: &quot;Galway-Mayo Institute of Technology&quot;},&quot;license&quot;: [&quot;CC-By 4.0&quot;],&quot;spatialCoverage&quot;:{&quot;@type&quot;: &quot;Place&quot;,&quot;geo&quot; : { &quot;@type&quot;: &quot;GeoShape&quot;, &quot;line&quot;: &quot;53.26774,-9.56025599 53.270113,-9.56818 53.23282,-9.575973 53.212198,-9.560421 53.20283,-9.433802 53.209427,-9.446743 53.20345,-9.3506 53.203037,-9.364669 53.17972,-9.358725 53.154492,-9.328668 53.057348,-9.405717 53.131935,-9.477158 53.190097,-9.533034 53.212198,-9.560421 53.195502,-9.470869 53.185433,-9.382307 53.187658,-9.444045 53.190433,-9.495681 53.212198,-9.560421 53.204065,-9.532641 53.152977,-9.465209 53.127599,-9.411612 53.185433,-9.382307 53.182535,-9.463258 53.168069,-9.518496 53.148345,-9.565631 53.17259,-9.586291 53.146112,-9.631122 53.178757,-9.653388 53.17018,-9.698193 53.214339,-9.586886 53.23282,-9.575973 53.196127,-9.685777 53.151299,-9.907939 53.05743,-9.877191 53.068916,-9.846734 53.091284,-9.882965 53.160089,-9.876013 53.192022,-9.715849 53.214184,-9.616424 53.23282,-9.575973 53.214339,-9.586886 53.190539,-9.644279 53.164249,-9.700145 53.190539,-9.644279 53.201903,-9.698569 53.199403,-9.749986 53.208836,-9.849636 53.117642,-9.9665 53.117273,-9.952769 53.160089,-9.876013 53.18021,-9.795927 53.214184,-9.616424 53.196077,-9.765496 53.157575,-10.138117 53.035649,-9.788682 53.01735,-9.774439 53.001392,-9.584849 53.067506,-9.634348 53.104861,-9.61191 53.153173,-9.591505 53.17259,-9.586291 53.23282,-9.575973 53.196394,-9.589376 53.129382,-9.602109 53.104861,-9.61191 52.978965,-9.81456 52.894838,-9.45389 52.899169,-9.525763 52.909892,-9.537975 52.980417,-9.48256 53.054379,-9.477811 53.097624,-9.511314 53.142616,-9.525755 53.191258,-9.553495 53.23282,-9.575973 53.270113,-9.56818 53.26774,-9.560256&quot;}},&quot;distribution&quot;: []}</gco:CharacterString>							</gmd:code>							<gmd:codeSpace>								<gco:CharacterString>https://schema.org</gco:CharacterString>							</gmd:codeSpace>						</gmd:RS_Identifier>					</gmd:identifier>                               </gmd:CI_Citation>                       </gmd:citation>			<gmd:abstract>				<gco:CharacterString>This cruise organised by Galway Mayo Institute of Technology (GMIT) was organised to use peer assisted learning to enable training of undergraduate degree students on the course in Applied Marine and Freshwater Biology in various fisheries, megafauna, benthic and oceanographic sampling methods at sea.  Those students who are on board a research vessel for a second or third time, whether undergraduate or postgraduate, will train (Peer Assisted Learning) students who are on board for the first time. This allows reinforcement of prior learning under the supervision of GMIT lecturers and postgrads. The aim is for the students to gain competencies in station position fixing, data logging, sampling and on-board sampling processing at sea. 

This cruise took place in October 2016 in Galway Bay on board the Marine Institute's R.V. Celtic Voyager.  Sampling and surveys conducted during the cruise include:
the use of box dredges, day grabs,  reineck box corer,  beam/otter trawl, plankton nets, CTD rosette, hydrophone and Remotely Operated Vehicles (ROV). 
 </gco:CharacterString>			</gmd:abstract>	<gmd:pointOfContact>				<gmd:CI_ResponsibleParty>					<gmd:organisationName>						<gco:CharacterString>Galway-Mayo Institute of Technology</gco:CharacterString>					</gmd:organisationName>					<gmd:contactInfo>						<gmd:CI_Contact>							<gmd:address>								<gmd:CI_Address>								<gmd:deliveryPoint>									<gco:CharacterString>GMIT Galway Campus</gco:CharacterString>								</gmd:deliveryPoint>								<gmd:city>									<gco:CharacterString>Dublin Road</gco:CharacterString>								</gmd:city>								<gmd:administrativeArea>									<gco:CharacterString>Galway</gco:CharacterString>								</gmd:administrativeArea>								<gmd:postalCode>									<gco:CharacterString>H91 T8NW</gco:CharacterString>								</gmd:postalCode>								<gmd:country>									<gco:CharacterString>Ireland</gco:CharacterString>								</gmd:country>									<gmd:electronicMailAddress>										<gco:CharacterString>researchoffice@gmit.ie</gco:CharacterString>									</gmd:electronicMailAddress>								</gmd:CI_Address>							</gmd:address>							<gmd:onlineResource>								<gmd:CI_OnlineResource>									<gmd:linkage>										<gmd:URL>http://www.gmit.ie/</gmd:URL>									</gmd:linkage>									<gmd:name>										<gco:CharacterString>Galway-Mayo Institute of Technology home page</gco:CharacterString>									</gmd:name>									<gmd:description>										<gco:CharacterString>Galway-Mayo Institute of Technology home page</gco:CharacterString>									</gmd:description>									<gmd:function>										<gmd:CI_OnLineFunctionCode codeList="http://www.isotc211.org/2005/resources/Codelist/gmxCodelists.xml#CI_OnLineFunctionCode" codeListValue="information"/>									</gmd:function>								</gmd:CI_OnlineResource>							</gmd:onlineResource>						</gmd:CI_Contact>					</gmd:contactInfo>					<gmd:role>						<gmd:CI_RoleCode codeList="http://standards.iso.org/ittf/PubliclyAvailableStandards/ISO_19139_Schemas/resources/Codelist/gmxCodelists.xml#CI_RoleCode" codeListValue="custodian">custodian</gmd:CI_RoleCode>					</gmd:role>				</gmd:CI_ResponsibleParty></gmd:pointOfContact>			<gmd:descriptiveKeywords>				<gmd:MD_Keywords>				<gmd:keyword>					<gmx:Anchor xlink:href="http://inspire.ec.europa.eu/theme/ac">Atmospheric conditions</gmx:Anchor>				</gmd:keyword>				<gmd:keyword>					<gmx:Anchor xlink:href="http://inspire.ec.europa.eu/theme/el">Elevation</gmx:Anchor>				</gmd:keyword>				<gmd:keyword>					<gmx:Anchor xlink:href="http://inspire.ec.europa.eu/theme/of">Oceanographic geographical features</gmx:Anchor>				</gmd:keyword>				<gmd:keyword>					<gmx:Anchor xlink:href="http://inspire.ec.europa.eu/theme/gg">Geographical grid systems</gmx:Anchor>				</gmd:keyword>				<gmd:keyword>					<gmx:Anchor xlink:href="http://inspire.ec.europa.eu/theme/mf">Meteorological geographical features</gmx:Anchor>				</gmd:keyword>					<gmd:type>						<gmd:MD_KeywordTypeCode codeList="http://www.isotc211.org/2005/resources/Codelist/gmxCodelists.xml#MD_KeywordTypeCode" codeListValue="theme">theme</gmd:MD_KeywordTypeCode>					</gmd:type>					<gmd:thesaurusName>						<gmd:CI_Citation>							<gmd:title>								<gmx:Anchor xlink:href="http://www.eionet.europa.eu/gemet/inspire_themes">GEMET - INSPIRE themes, version 1.0</gmx:Anchor>							</gmd:title>							<gmd:date>								<gmd:CI_Date>									<gmd:date>										<gco:Date>2008-06-01</gco:Date>									</gmd:date>									<gmd:dateType>										<gmd:CI_DateTypeCode codeList="http://standards.iso.org/ittf/PubliclyAvailableStandards/ISO_19139_Schemas/resources/Codelist/ML_gmxCodelists.xml#CI_DateTypeCode" codeListValue="publication">publication</gmd:CI_DateTypeCode>									</gmd:dateType>							</gmd:CI_Date>						</gmd:date>					</gmd:CI_Citation>				</gmd:thesaurusName>				</gmd:MD_Keywords>			</gmd:descriptiveKeywords>			<gmd:descriptiveKeywords>				<gmd:MD_Keywords>				<gmd:keyword>					<gmx:Anchor xlink:href="http://vocab.nerc.ac.uk/collection/P02/current/CAPH/">Air pressure</gmx:Anchor>				</gmd:keyword>				<gmd:keyword>					<gmx:Anchor xlink:href="http://vocab.nerc.ac.uk/collection/P02/current/CDTA/">Air temperature</gmx:Anchor>				</gmd:keyword>				<gmd:keyword>					<gmx:Anchor xlink:href="http://vocab.nerc.ac.uk/collection/P02/current/AHGT/">Vertical spatial coordinates</gmx:Anchor>				</gmd:keyword>				<gmd:keyword>					<gmx:Anchor xlink:href="http://vocab.nerc.ac.uk/collection/P02/current/ALAT/">Horizontal spatial co-ordinates</gmx:Anchor>				</gmd:keyword>				<gmd:keyword>					<gmx:Anchor xlink:href="http://vocab.nerc.ac.uk/collection/P02/current/HEAD/">Platform or instrument orientation</gmx:Anchor>				</gmd:keyword>				<gmd:keyword>					<gmx:Anchor xlink:href="http://vocab.nerc.ac.uk/collection/P02/current/CHUM/">Atmospheric Humidity</gmx:Anchor>				</gmd:keyword>				<gmd:keyword>					<gmx:Anchor xlink:href="http://vocab.nerc.ac.uk/collection/P02/current/EWSB/">Wind strength and direction</gmx:Anchor>				</gmd:keyword>					<gmd:thesaurusName>						<gmd:CI_Citation>							<gmd:title>								<gmx:Anchor xlink:href="http://vocab.nerc.ac.uk/collection/P02/current/">SeaDataNet Parameter Discovery Vocabulary</gmx:Anchor>							</gmd:title>							<gmd:date>								<gmd:CI_Date>									<gmd:date>										<gco:Date>2018-04-05</gco:Date>									</gmd:date>									<gmd:dateType>										<gmd:CI_DateTypeCode codeList="http://standards.iso.org/ittf/PubliclyAvailableStandards/ISO_19139_Schemas/resources/Codelist/ML_gmxCodelists.xml#CI_DateTypeCode" codeListValue="revision">revision</gmd:CI_DateTypeCode>									</gmd:dateType>							</gmd:CI_Date>						</gmd:date>					</gmd:CI_Citation>				</gmd:thesaurusName>				</gmd:MD_Keywords>			</gmd:descriptiveKeywords>			<gmd:descriptiveKeywords>				<gmd:MD_Keywords>				<gmd:keyword>					<gmx:Anchor xlink:href="http://vocab.nerc.ac.uk/collection/P01/current/CAPHZZ01/">Pressure (measured variable) exerted by the atmosphere</gmx:Anchor>				</gmd:keyword>				<gmd:keyword>					<gmx:Anchor xlink:href="http://vocab.nerc.ac.uk/collection/P01/current/CTMPZZ01/">Temperature of the atmosphere</gmx:Anchor>				</gmd:keyword>				<gmd:keyword>					<gmx:Anchor xlink:href="http://vocab.nerc.ac.uk/collection/P02/current/AYMD/">Date and time</gmx:Anchor>				</gmd:keyword>				<gmd:keyword>					<gmx:Anchor xlink:href="http://vocab.nerc.ac.uk/collection/P01/current/ADEPZZ01/">Depth below surface of the water body</gmx:Anchor>				</gmd:keyword>				<gmd:keyword>					<gmx:Anchor xlink:href="http://vocab.nerc.ac.uk/collection/P01/current/ALATZZ01/">Latitude north</gmx:Anchor>				</gmd:keyword>				<gmd:keyword>					<gmx:Anchor xlink:href="http://vocab.nerc.ac.uk/collection/P01/current/ALONZZ01/">Longitude east</gmx:Anchor>				</gmd:keyword>				<gmd:keyword>					<gmx:Anchor xlink:href="http://vocab.nerc.ac.uk/collection/P07/current/I2NHBPFG/">Platform Id</gmx:Anchor>				</gmd:keyword>				<gmd:keyword>					<gmx:Anchor xlink:href="http://vocab.nerc.ac.uk/collection/P07/current/CH3BBTYJ/">Platform Name</gmx:Anchor>				</gmd:keyword>				<gmd:keyword>					<gmx:Anchor xlink:href="http://vocab.nerc.ac.uk/collection/P01/current/HDNGGP01/">Orientation (horizontal relative to true north) of measurement device {heading}</gmx:Anchor>				</gmd:keyword>				<gmd:keyword>					<gmx:Anchor xlink:href="http://vocab.nerc.ac.uk/collection/P01/current/CHUMZZ01/">Relative humidity of the atmosphere</gmx:Anchor>				</gmd:keyword>				<gmd:keyword>					<gmx:Anchor xlink:href="http://vocab.nerc.ac.uk/collection/P07/current/CFSN0376/">Sea Surface Salinity</gmx:Anchor>				</gmd:keyword>				<gmd:keyword>					<gmx:Anchor xlink:href="http://vocab.nerc.ac.uk/collection/P07/current/CFSN0381/">Sea Surface Temperature</gmx:Anchor>				</gmd:keyword>				<gmd:keyword>					<gmx:Anchor xlink:href="http://vocab.nerc.ac.uk/collection/P01/current/EWDAZZ01/">Direction from of wind relative to True North {wind direction} in the atmosphere</gmx:Anchor>				</gmd:keyword>				<gmd:keyword>					<gmx:Anchor xlink:href="http://vocab.nerc.ac.uk/collection/P01/current/EWSBZZ01/">Speed of wind {wind speed} in the atmosphere</gmx:Anchor>				</gmd:keyword>				<gmd:keyword>					<gmx:Anchor xlink:href="http://vocab.nerc.ac.uk/collection/P01/current/EGTSZZ01/">Speed of wind (gust) {wind speed} in the atmosphere</gmx:Anchor>				</gmd:keyword>					<gmd:thesaurusName>						<gmd:CI_Citation>							<gmd:title>								<gmx:Anchor xlink:href="http://vocab.nerc.ac.uk/collection/P01/current/">BODC Parameter Usage Vocabulary</gmx:Anchor>							</gmd:title>							<gmd:date>								<gmd:CI_Date>									<gmd:date>										<gco:Date>2008-06-01</gco:Date>									</gmd:date>									<gmd:dateType>										<gmd:CI_DateTypeCode codeList="http://standards.iso.org/ittf/PubliclyAvailableStandards/ISO_19139_Schemas/resources/Codelist/ML_gmxCodelists.xml#CI_DateTypeCode" codeListValue="revision">revision</gmd:CI_DateTypeCode>									</gmd:dateType>							</gmd:CI_Date>						</gmd:date>					</gmd:CI_Citation>				</gmd:thesaurusName>				</gmd:MD_Keywords>			</gmd:descriptiveKeywords>			<gmd:descriptiveKeywords>				<gmd:MD_Keywords>				<gmd:keyword>					<gmx:Anchor xlink:href="http://vocab.nerc.ac.uk/collection/P03/current/M010/">Meteorology</gmx:Anchor>				</gmd:keyword>				<gmd:keyword>					<gmx:Anchor xlink:href="http://vocab.nerc.ac.uk/collection/P03/current/Z005/">Administration and dimensions</gmx:Anchor>				</gmd:keyword>					<gmd:thesaurusName>						<gmd:CI_Citation>							<gmd:title>								<gmx:Anchor xlink:href="http://vocab.nerc.ac.uk/collection/P03/current/">SeaDataNet Agreed Parameter Groups</gmx:Anchor>							</gmd:title>							<gmd:date>								<gmd:CI_Date>									<gmd:date>										<gco:Date>2017-05-03</gco:Date>									</gmd:date>									<gmd:dateType>										<gmd:CI_DateTypeCode codeList="http://standards.iso.org/ittf/PubliclyAvailableStandards/ISO_19139_Schemas/resources/Codelist/ML_gmxCodelists.xml#CI_DateTypeCode" codeListValue="revision">revision</gmd:CI_DateTypeCode>									</gmd:dateType>							</gmd:CI_Date>						</gmd:date>					</gmd:CI_Citation>				</gmd:thesaurusName>				</gmd:MD_Keywords>			</gmd:descriptiveKeywords>			<gmd:descriptiveKeywords>				<gmd:MD_Keywords>				<gmd:keyword>					<gmx:Anchor xlink:href="http://vocab.nerc.ac.uk/collection/P08/current/DS05/">Atmosphere</gmx:Anchor>				</gmd:keyword>				<gmd:keyword>					<gmx:Anchor xlink:href="http://vocab.nerc.ac.uk/collection/P08/current/DS07/">Administration and dimensions</gmx:Anchor>				</gmd:keyword>					<gmd:type>						<gmd:MD_KeywordTypeCode codeList="http://www.isotc211.org/2005/resources/Codelist/gmxCodelists.xml#MD_KeywordTypeCode" codeListValue="discipline">discipline</gmd:MD_KeywordTypeCode>					</gmd:type>					<gmd:thesaurusName>						<gmd:CI_Citation>							<gmd:title>								<gmx:Anchor xlink:href="http://vocab.nerc.ac.uk/collection/P08/current/">SeaDataNet Disciplines</gmx:Anchor>							</gmd:title>							<gmd:date>								<gmd:CI_Date>									<gmd:date>										<gco:Date>2017-02-03</gco:Date>									</gmd:date>									<gmd:dateType>										<gmd:CI_DateTypeCode codeList="http://standards.iso.org/ittf/PubliclyAvailableStandards/ISO_19139_Schemas/resources/Codelist/ML_gmxCodelists.xml#CI_DateTypeCode" codeListValue="revision">revision</gmd:CI_DateTypeCode>									</gmd:dateType>							</gmd:CI_Date>						</gmd:date>					</gmd:CI_Citation>				</gmd:thesaurusName>				</gmd:MD_Keywords>			</gmd:descriptiveKeywords>	<gmd:descriptiveKeywords>			<gmd:MD_Keywords>			<gmd:keyword>				<gmx:Anchor xlink:href="http://vocab.nerc.ac.uk/collection/L22/current/TOOL0667/">Sea-Bird SBE 21 Thermosalinograph</gmx:Anchor>			</gmd:keyword>			<gmd:keyword>				<gmx:Anchor xlink:href="http://vocab.nerc.ac.uk/collection/L22/current/TOOL0269/">anemometer</gmx:Anchor>			</gmd:keyword>			<gmd:keyword>				<gmx:Anchor xlink:href="http://vocab.nerc.ac.uk/collection/L22/current/TOOL0081/">Vaisala HMP temperature and humidity sensor</gmx:Anchor>			</gmd:keyword>				<gmd:thesaurusName>					<gmd:CI_Citation>						<gmd:title>							<gmx:Anchor xlink:href="http://vocab.nerc.ac.uk/collection/L22/current/">SeaVoX Device Catalogue</gmx:Anchor>						</gmd:title>						<gmd:date>							<gmd:CI_Date>								<gmd:date>									<gco:Date>2018-06-14</gco:Date>								</gmd:date>								<gmd:dateType>									<gmd:CI_DateTypeCode codeList="http://standards.iso.org/ittf/PubliclyAvailableStandards/ISO_19139_Schemas/resources/Codelist/ML_gmxCodelists.xml#CI_DateTypeCode" codeListValue="revision">revision</gmd:CI_DateTypeCode>								</gmd:dateType>						</gmd:CI_Date>					</gmd:date>				</gmd:CI_Citation>			</gmd:thesaurusName>			</gmd:MD_Keywords>		</gmd:descriptiveKeywords>	<gmd:descriptiveKeywords>			<gmd:MD_Keywords>			<gmd:keyword>				<gmx:Anchor xlink:href="http://vocab.nerc.ac.uk/collection/L05/current/133/">Thermosalinographs</gmx:Anchor>			</gmd:keyword>			<gmd:keyword>				<gmx:Anchor xlink:href="http://vocab.nerc.ac.uk/collection/L05/current/101/">anemometers</gmx:Anchor>			</gmd:keyword>			<gmd:keyword>				<gmx:Anchor xlink:href="http://vocab.nerc.ac.uk/collection/L05/current/102/">meteorological packages</gmx:Anchor>			</gmd:keyword>				<gmd:thesaurusName>					<gmd:CI_Citation>						<gmd:title>							<gmx:Anchor xlink:href="http://vocab.nerc.ac.uk/collection/L05/current/">SeaDataNet Device Categories</gmx:Anchor>						</gmd:title>						<gmd:date>							<gmd:CI_Date>								<gmd:date>									<gco:Date>2018-04-07</gco:Date>								</gmd:date>								<gmd:dateType>									<gmd:CI_DateTypeCode codeList="http://standards.iso.org/ittf/PubliclyAvailableStandards/ISO_19139_Schemas/resources/Codelist/ML_gmxCodelists.xml#CI_DateTypeCode" codeListValue="revision">revision</gmd:CI_DateTypeCode>								</gmd:dateType>						</gmd:CI_Date>					</gmd:date>				</gmd:CI_Citation>			</gmd:thesaurusName>			</gmd:MD_Keywords>		</gmd:descriptiveKeywords>	<gmd:descriptiveKeywords>			<gmd:MD_Keywords>			<gmd:keyword>				<gmx:Anchor xlink:href="http://vocab.nerc.ac.uk/collection/L06/current/31/">research vessel</gmx:Anchor>			</gmd:keyword>				<gmd:thesaurusName>					<gmd:CI_Citation>						<gmd:title>							<gmx:Anchor xlink:href="http://vocab.nerc.ac.uk/collection/L06/current/">SeaVoX Platform Categories</gmx:Anchor>						</gmd:title>						<gmd:date>							<gmd:CI_Date>								<gmd:date>									<gco:Date>2018-04-07</gco:Date>								</gmd:date>								<gmd:dateType>									<gmd:CI_DateTypeCode codeList="http://standards.iso.org/ittf/PubliclyAvailableStandards/ISO_19139_Schemas/resources/Codelist/ML_gmxCodelists.xml#CI_DateTypeCode" codeListValue="revision">revision</gmd:CI_DateTypeCode>								</gmd:dateType>						</gmd:CI_Date>					</gmd:date>				</gmd:CI_Citation>			</gmd:thesaurusName>			</gmd:MD_Keywords>		</gmd:descriptiveKeywords>	<gmd:descriptiveKeywords>			<gmd:MD_Keywords>			<gmd:keyword>				<gmx:Anchor xlink:href="http://vocab.nerc.ac.uk/collection/C17/current/45CV">RV Celtic Voyager</gmx:Anchor>			</gmd:keyword>				<gmd:thesaurusName>					<gmd:CI_Citation>						<gmd:title>							<gmx:Anchor xlink:href="http://vocab.nerc.ac.uk/collection/C17/current/">ICES Platform Codes</gmx:Anchor>						</gmd:title>						<gmd:date>							<gmd:CI_Date>								<gmd:date>									<gco:Date>2018-04-07</gco:Date>								</gmd:date>								<gmd:dateType>									<gmd:CI_DateTypeCode codeList="http://standards.iso.org/ittf/PubliclyAvailableStandards/ISO_19139_Schemas/resources/Codelist/ML_gmxCodelists.xml#CI_DateTypeCode" codeListValue="revision">revision</gmd:CI_DateTypeCode>								</gmd:dateType>						</gmd:CI_Date>					</gmd:date>				</gmd:CI_Citation>			</gmd:thesaurusName>			</gmd:MD_Keywords>		</gmd:descriptiveKeywords>			<gmd:resourceConstraints>				<gmd:MD_Constraints>					<gmd:useLimitation>						<gco:CharacterString>Consult license for use limitations</gco:CharacterString>					</gmd:useLimitation>					<gmd:useLimitation>						<gmd:MD_ClassificationCode codeList="http://data.marine.ie/resources/Codelist/gmxCodelists.xml#MI_RestrictionCode" codeListValue="cc-by4.0">CC-By 4.0</gmd:MD_ClassificationCode>					</gmd:useLimitation>				</gmd:MD_Constraints>			</gmd:resourceConstraints>			<gmd:resourceConstraints>       		<gmd:MD_LegalConstraints>             	<gmd:accessConstraints>						<gmd:MD_RestrictionCode codeList="http://standards.iso.org/ittf/PubliclyAvailableStandards/ISO_19139_Schemas/resources/Codelist/gmxCodelists.xml#MD_RestrictionCode" codeListValue="license">license</gmd:MD_RestrictionCode>					</gmd:accessConstraints>				</gmd:MD_LegalConstraints>			</gmd:resourceConstraints>		<gmd:aggregationInfo>		  <gmd:MD_AggregateInformation id="instrument-00001">			<gmd:aggregateDataSetIdentifier>				<gmd:MD_Identifier>					<gmd:code>						<gco:CharacterString>ie.marine.data:instrument.45</gco:CharacterString>					</gmd:code>				</gmd:MD_Identifier>			</gmd:aggregateDataSetIdentifier>			<gmd:associationType>				<gmd:DS_AssociationTypeCode codeList="http://www.isotc211.org/2005/resources/Codelist/gmxCodelists.xml#DS_AssociationTypeCode" codeListValue="crossReference">crossReference</gmd:DS_AssociationTypeCode>			</gmd:associationType>			<gmd:initiativeType><gmd:DS_InitiativeTypeCode codeList="http://www.isotc211.org/2005/resources/Codelist/gmxCodelists.xml#DS_InitiativeTypeCode" codeListValue="sensor">sensor</gmd:DS_InitiativeTypeCode>			</gmd:initiativeType>		  </gmd:MD_AggregateInformation>		</gmd:aggregationInfo>		<gmd:aggregationInfo>		  <gmd:MD_AggregateInformation id="instrument-00002">			<gmd:aggregateDataSetIdentifier>				<gmd:MD_Identifier>					<gmd:code>						<gco:CharacterString>ie.marine.data:instrument.195</gco:CharacterString>					</gmd:code>				</gmd:MD_Identifier>			</gmd:aggregateDataSetIdentifier>			<gmd:associationType>				<gmd:DS_AssociationTypeCode codeList="http://www.isotc211.org/2005/resources/Codelist/gmxCodelists.xml#DS_AssociationTypeCode" codeListValue="crossReference">crossReference</gmd:DS_AssociationTypeCode>			</gmd:associationType>			<gmd:initiativeType><gmd:DS_InitiativeTypeCode codeList="http://www.isotc211.org/2005/resources/Codelist/gmxCodelists.xml#DS_InitiativeTypeCode" codeListValue="sensor">sensor</gmd:DS_InitiativeTypeCode>			</gmd:initiativeType>		  </gmd:MD_AggregateInformation>		</gmd:aggregationInfo>		<gmd:aggregationInfo>		  <gmd:MD_AggregateInformation id="instrument-00003">			<gmd:aggregateDataSetIdentifier>				<gmd:MD_Identifier>					<gmd:code>						<gco:CharacterString>ie.marine.data:instrument.198</gco:CharacterString>					</gmd:code>				</gmd:MD_Identifier>			</gmd:aggregateDataSetIdentifier>			<gmd:associationType>				<gmd:DS_AssociationTypeCode codeList="http://www.isotc211.org/2005/resources/Codelist/gmxCodelists.xml#DS_AssociationTypeCode" codeListValue="crossReference">crossReference</gmd:DS_AssociationTypeCode>			</gmd:associationType>			<gmd:initiativeType><gmd:DS_InitiativeTypeCode codeList="http://www.isotc211.org/2005/resources/Codelist/gmxCodelists.xml#DS_InitiativeTypeCode" codeListValue="sensor">sensor</gmd:DS_InitiativeTypeCode>			</gmd:initiativeType>		  </gmd:MD_AggregateInformation>		</gmd:aggregationInfo>		<gmd:aggregationInfo>		  <gmd:MD_AggregateInformation id="instrument-00004">			<gmd:aggregateDataSetIdentifier>				<gmd:MD_Identifier>					<gmd:code>						<gco:CharacterString>ie.marine.data:instrument.199</gco:CharacterString>					</gmd:code>				</gmd:MD_Identifier>			</gmd:aggregateDataSetIdentifier>			<gmd:associationType>				<gmd:DS_AssociationTypeCode codeList="http://www.isotc211.org/2005/resources/Codelist/gmxCodelists.xml#DS_AssociationTypeCode" codeListValue="crossReference">crossReference</gmd:DS_AssociationTypeCode>			</gmd:associationType>			<gmd:initiativeType><gmd:DS_InitiativeTypeCode codeList="http://www.isotc211.org/2005/resources/Codelist/gmxCodelists.xml#DS_InitiativeTypeCode" codeListValue="sensor">sensor</gmd:DS_InitiativeTypeCode>			</gmd:initiativeType>		  </gmd:MD_AggregateInformation>		</gmd:aggregationInfo>		<gmd:aggregationInfo>		  <gmd:MD_AggregateInformation id="platform">			<gmd:aggregateDataSetIdentifier>				<gmd:MD_Identifier>					<gmd:code>						<gco:CharacterString>ie.marine.data:platform.34</gco:CharacterString>					</gmd:code>				</gmd:MD_Identifier>			</gmd:aggregateDataSetIdentifier>			<gmd:associationType>				<gmd:DS_AssociationTypeCode codeList="http://www.isotc211.org/2005/resources/Codelist/gmxCodelists.xml#DS_AssociationTypeCode" codeListValue="crossReference">crossReference</gmd:DS_AssociationTypeCode>			</gmd:associationType>			<gmd:initiativeType><gmd:DS_InitiativeTypeCode codeList="http://www.isotc211.org/2005/resources/Codelist/gmxCodelists.xml#DS_InitiativeTypeCode" codeListValue="platform">platform</gmd:DS_InitiativeTypeCode>			</gmd:initiativeType>		  </gmd:MD_AggregateInformation>		</gmd:aggregationInfo>		<gmd:aggregationInfo>		  <gmd:MD_AggregateInformation>			<gmd:aggregateDataSetIdentifier>				<gmd:MD_Identifier>					<gmd:code>						<gco:CharacterString>ie.marine.data:dataset.845</gco:CharacterString>					</gmd:code>				</gmd:MD_Identifier>			</gmd:aggregateDataSetIdentifier>			<gmd:associationType>				<gmd:DS_AssociationTypeCode codeList="http://www.isotc211.org/2005/resources/Codelist/gmxCodelists.xml#DS_AssociationTypeCode" codeListValue="crossReference">crossReference</gmd:DS_AssociationTypeCode>			</gmd:associationType>			<gmd:initiativeType><gmd:DS_InitiativeTypeCode codeList="http://www.isotc211.org/2005/resources/Codelist/gmxCodelists.xml#DS_InitiativeTypeCode" codeListValue="collection">collection</gmd:DS_InitiativeTypeCode>			</gmd:initiativeType>		  </gmd:MD_AggregateInformation>		</gmd:aggregationInfo>		<gmd:aggregationInfo>			<gmd:MD_AggregateInformation>				<gmd:aggregateDataSetName>					<gmd:CI_Citation>						<gmd:title>							<gco:CharacterString>Strategic Marine Alliance for Research and Training (SMART)</gco:CharacterString>						</gmd:title>					<gmd:date>						<gmd:CI_Date>							 <gmd:date>								<gco:Date>2012-01-01</gco:Date>							 </gmd:date>							<gmd:dateType>								<gmd:CI_DateTypeCode codeList="http://www.ngdc.noaa.gov/metadata/published/xsd/schema/resources/Codelist/gmxCodelists.xml#CI_DateTypeCode" codeListValue="adopted">adopted</gmd:CI_DateTypeCode>							</gmd:dateType>						</gmd:CI_Date>					</gmd:date>				<gmd:citedResponsibleParty>					<gmd:CI_ResponsibleParty>						<gmd:organisationName>							<gco:CharacterString>Galway-Mayo Institute of Technology</gco:CharacterString>						</gmd:organisationName>						<gmd:contactInfo>							<gmd:CI_Contact>								<gmd:address>									<gmd:CI_Address>								<gmd:deliveryPoint>									<gco:CharacterString>GMIT Galway Campus</gco:CharacterString>								</gmd:deliveryPoint>								<gmd:city>									<gco:CharacterString>Dublin Road</gco:CharacterString>								</gmd:city>								<gmd:administrativeArea>									<gco:CharacterString>Galway</gco:CharacterString>								</gmd:administrativeArea>								<gmd:postalCode>									<gco:CharacterString>H91 T8NW</gco:CharacterString>								</gmd:postalCode>								<gmd:country>									<gco:CharacterString>Ireland</gco:CharacterString>								</gmd:country>										<gmd:electronicMailAddress>											<gco:CharacterString>researchoffice@gmit.ie</gco:CharacterString>										</gmd:electronicMailAddress>									</gmd:CI_Address>								</gmd:address>							<gmd:onlineResource>								<gmd:CI_OnlineResource>									<gmd:linkage>										<gmd:URL>http://www.gmit.ie/</gmd:URL>									</gmd:linkage>									<gmd:name>										<gco:CharacterString>Galway-Mayo Institute of Technology home page</gco:CharacterString>									</gmd:name>									<gmd:description>										<gco:CharacterString>Galway-Mayo Institute of Technology home page</gco:CharacterString>									</gmd:description>									<gmd:function>										<gmd:CI_OnLineFunctionCode codeList="http://www.isotc211.org/2005/resources/Codelist/gmxCodelists.xml#CI_OnLineFunctionCode" codeListValue="information"/>									</gmd:function>								</gmd:CI_OnlineResource>							</gmd:onlineResource>							</gmd:CI_Contact>						</gmd:contactInfo>						<gmd:role>							<gmd:CI_RoleCode codeList="http://standards.iso.org/ittf/PubliclyAvailableStandards/ISO_19139_Schemas/resources/Codelist/gmxCodelists.xml#CI_RoleCode" codeListValue="principalInvestigator">principalInvestigator</gmd:CI_RoleCode>						</gmd:role>					</gmd:CI_ResponsibleParty>				</gmd:citedResponsibleParty>				<gmd:citedResponsibleParty>					<gmd:CI_ResponsibleParty>						<gmd:organisationName>							<gco:CharacterString>Marine Institute</gco:CharacterString>						</gmd:organisationName>						<gmd:contactInfo>							<gmd:CI_Contact>								<gmd:address>									<gmd:CI_Address>								<gmd:deliveryPoint>									<gco:CharacterString>Rinville</gco:CharacterString>								</gmd:deliveryPoint>								<gmd:city>									<gco:CharacterString>Oranmore</gco:CharacterString>								</gmd:city>								<gmd:administrativeArea>									<gco:CharacterString>Galway</gco:CharacterString>								</gmd:administrativeArea>								<gmd:postalCode>									<gco:CharacterString>H91 R673</gco:CharacterString>								</gmd:postalCode>								<gmd:country>									<gco:CharacterString>Ireland</gco:CharacterString>								</gmd:country>										<gmd:electronicMailAddress>											<gco:CharacterString>datarequests@marine.ie</gco:CharacterString>										</gmd:electronicMailAddress>									</gmd:CI_Address>								</gmd:address>							<gmd:onlineResource>								<gmd:CI_OnlineResource>									<gmd:linkage>										<gmd:URL>http://www.marine.ie</gmd:URL>									</gmd:linkage>									<gmd:name>										<gco:CharacterString>Marine Institute home page</gco:CharacterString>									</gmd:name>									<gmd:description>										<gco:CharacterString>Marine Institute home page</gco:CharacterString>									</gmd:description>									<gmd:function>										<gmd:CI_OnLineFunctionCode codeList="http://www.isotc211.org/2005/resources/Codelist/gmxCodelists.xml#CI_OnLineFunctionCode" codeListValue="information"/>									</gmd:function>								</gmd:CI_OnlineResource>							</gmd:onlineResource>							</gmd:CI_Contact>						</gmd:contactInfo>						<gmd:role>							<gmd:CI_RoleCode codeList="http://www.ngdc.noaa.gov/metadata/published/xsd/schema/resources/Codelist/gmxCodelists.xml#CI_RoleCode" codeListValue="contributor">contributor</gmd:CI_RoleCode>						</gmd:role>					</gmd:CI_ResponsibleParty>				</gmd:citedResponsibleParty>											<gmd:otherCitationDetails>						<gco:CharacterString>The Strategic Marine Alliance for Research and Training (SMART) is a marine science partnership programme designed to further develop capacity in carrying out offshore operations on board research vessels for third level students of marine-related science and technologies.  This strategic collaborative inter-institutional programme is led and funded by Irish Higher Education Institutions (HEIs) and the Marine Institute and is also supported by the Higher Education Authority (HEA).  Key Objectives   1. Develop integrated delivery of specifically tailored accredited offshore training courses for students of marine-related science and technologies, nationally and internationally.  2. Facilitate the creation of new skills and expertise which will be of direct benefit to science and industry, particularly in new and emerging technologies.  3. Increase cost effective collaboration and cooperation between a diverse range of independent higher education institutes and semi-state agencies with different institutional strengths.  4. Enhance value for money through coordinated use of national infrastructure and facilities to increase national marine science research capacity.  5. Act as a framework for further collaborative arrangements in marine research and training.  6. Ultimately establish Ireland as a world-class training centre for ship-based marine science and technology. </gco:CharacterString>					</gmd:otherCitationDetails>					</gmd:CI_Citation>				</gmd:aggregateDataSetName>				<gmd:associationType>					<gmd:DS_AssociationTypeCode codeList="http://www.isotc211.org/2005/resources/Codelist/gmxCodelists.xml#DS_AssociationTypeCode" codeListValue="largerWorkCitation"/>				</gmd:associationType>				<gmd:initiativeType>					<gmd:DS_InitiativeTypeCode codeList="http://www.isotc211.org/2005/resources/Codelist/gmxCodelists.xml#DS_InitiativeTypeCode" codeListValue="project"/>				</gmd:initiativeType>			</gmd:MD_AggregateInformation>		</gmd:aggregationInfo>			<gmd:language>				<gmd:LanguageCode codeList="http://www.loc.gov/standards/iso639-2/" codeListValue="eng">eng</gmd:LanguageCode>			</gmd:language>		<gmd:topicCategory>			<gmd:MD_TopicCategoryCode>climatologyMeteorologyAtmosphere</gmd:MD_TopicCategoryCode>		</gmd:topicCategory>		<gmd:topicCategory>			<gmd:MD_TopicCategoryCode>elevation</gmd:MD_TopicCategoryCode>		</gmd:topicCategory>		<gmd:topicCategory>			<gmd:MD_TopicCategoryCode>location</gmd:MD_TopicCategoryCode>		</gmd:topicCategory>			<gmd:extent>				<gmd:EX_Extent>					<gmd:temporalElement>						<gmd:EX_TemporalExtent>							<gmd:extent>								<gml:TimePeriod gml:id="timeperiod1">									<gml:beginPosition>2016-10-22T00:00:00</gml:beginPosition>                                                       <gml:endPosition>2016-10-31T23:59:59</gml:endPosition>								</gml:TimePeriod>							</gmd:extent>						</gmd:EX_TemporalExtent>					</gmd:temporalElement>				</gmd:EX_Extent>			</gmd:extent>			<gmd:extent>				<gmd:EX_Extent>					<gmd:geographicElement>						<gmd:EX_GeographicBoundingBox>							<gmd:westBoundLongitude>								<gco:Decimal>-10.138117</gco:Decimal>							</gmd:westBoundLongitude>							<gmd:eastBoundLongitude>								<gco:Decimal>-9.328668</gco:Decimal>							</gmd:eastBoundLongitude>							<gmd:southBoundLatitude>								<gco:Decimal>52.894838</gco:Decimal>							</gmd:southBoundLatitude>							<gmd:northBoundLatitude>								<gco:Decimal>53.270113</gco:Decimal>							</gmd:northBoundLatitude>						</gmd:EX_GeographicBoundingBox>					</gmd:geographicElement>			<gmd:geographicElement>				<gmd:EX_BoundingPolygon>					<gmd:extentTypeCode>						<gco:Boolean>true</gco:Boolean>					</gmd:extentTypeCode>					<gmd:polygon>					<gml:LineString gml:id="ie.marine.data..feature.314" srsName="urn:ogc:def:crs:EPSG::3857">						<gml:identifier codeSpace="http://data.marine.ie">ie.marine.data:feature.314</gml:identifier><gml:pos>-9.56025599 53.26774</gml:pos> <gml:pos>-9.56818 53.270113</gml:pos> <gml:pos>-9.575973 53.23282</gml:pos> <gml:pos>-9.560421 53.212198</gml:pos> <gml:pos>-9.433802 53.20283</gml:pos> <gml:pos>-9.446743 53.209427</gml:pos> <gml:pos>-9.3506 53.20345</gml:pos> <gml:pos>-9.364669 53.203037</gml:pos> <gml:pos>-9.358725 53.17972</gml:pos> <gml:pos>-9.328668 53.154492</gml:pos> <gml:pos>-9.405717 53.057348</gml:pos> <gml:pos>-9.477158 53.131935</gml:pos> <gml:pos>-9.533034 53.190097</gml:pos> <gml:pos>-9.560421 53.212198</gml:pos> <gml:pos>-9.470869 53.195502</gml:pos> <gml:pos>-9.382307 53.185433</gml:pos> <gml:pos>-9.444045 53.187658</gml:pos> <gml:pos>-9.495681 53.190433</gml:pos> <gml:pos>-9.560421 53.212198</gml:pos> <gml:pos>-9.532641 53.204065</gml:pos> <gml:pos>-9.465209 53.152977</gml:pos> <gml:pos>-9.411612 53.127599</gml:pos> <gml:pos>-9.382307 53.185433</gml:pos> <gml:pos>-9.463258 53.182535</gml:pos> <gml:pos>-9.518496 53.168069</gml:pos> <gml:pos>-9.565631 53.148345</gml:pos> <gml:pos>-9.586291 53.17259</gml:pos> <gml:pos>-9.631122 53.146112</gml:pos> <gml:pos>-9.653388 53.178757</gml:pos> <gml:pos>-9.698193 53.17018</gml:pos> <gml:pos>-9.586886 53.214339</gml:pos> <gml:pos>-9.575973 53.23282</gml:pos> <gml:pos>-9.685777 53.196127</gml:pos> <gml:pos>-9.907939 53.151299</gml:pos> <gml:pos>-9.877191 53.05743</gml:pos> <gml:pos>-9.846734 53.068916</gml:pos> <gml:pos>-9.882965 53.091284</gml:pos> <gml:pos>-9.876013 53.160089</gml:pos> <gml:pos>-9.715849 53.192022</gml:pos> <gml:pos>-9.616424 53.214184</gml:pos> <gml:pos>-9.575973 53.23282</gml:pos> <gml:pos>-9.586886 53.214339</gml:pos> <gml:pos>-9.644279 53.190539</gml:pos> <gml:pos>-9.700145 53.164249</gml:pos> <gml:pos>-9.644279 53.190539</gml:pos> <gml:pos>-9.698569 53.201903</gml:pos> <gml:pos>-9.749986 53.199403</gml:pos> <gml:pos>-9.849636 53.208836</gml:pos> <gml:pos>-9.9665 53.117642</gml:pos> <gml:pos>-9.952769 53.117273</gml:pos> <gml:pos>-9.876013 53.160089</gml:pos> <gml:pos>-9.795927 53.18021</gml:pos> <gml:pos>-9.616424 53.214184</gml:pos> <gml:pos>-9.765496 53.196077</gml:pos> <gml:pos>-10.138117 53.157575</gml:pos> <gml:pos>-9.788682 53.035649</gml:pos> <gml:pos>-9.774439 53.01735</gml:pos> <gml:pos>-9.584849 53.001392</gml:pos> <gml:pos>-9.634348 53.067506</gml:pos> <gml:pos>-9.61191 53.104861</gml:pos> <gml:pos>-9.591505 53.153173</gml:pos> <gml:pos>-9.586291 53.17259</gml:pos> <gml:pos>-9.575973 53.23282</gml:pos> <gml:pos>-9.589376 53.196394</gml:pos> <gml:pos>-9.602109 53.129382</gml:pos> <gml:pos>-9.61191 53.104861</gml:pos> <gml:pos>-9.81456 52.978965</gml:pos> <gml:pos>-9.45389 52.894838</gml:pos> <gml:pos>-9.525763 52.899169</gml:pos> <gml:pos>-9.537975 52.909892</gml:pos> <gml:pos>-9.48256 52.980417</gml:pos> <gml:pos>-9.477811 53.054379</gml:pos> <gml:pos>-9.511314 53.097624</gml:pos> <gml:pos>-9.525755 53.142616</gml:pos> <gml:pos>-9.553495 53.191258</gml:pos> <gml:pos>-9.575973 53.23282</gml:pos> <gml:pos>-9.56818 53.270113</gml:pos> <gml:pos>-9.560256 53.26774</gml:pos>					</gml:LineString>					</gmd:polygon>				</gmd:EX_BoundingPolygon>			</gmd:geographicElement>				</gmd:EX_Extent>			</gmd:extent>               </gmd:MD_DataIdentification>       </gmd:identificationInfo>		  <gmd:dataQualityInfo>			<gmd:DQ_DataQuality>				<gmd:scope>					<gmd:DQ_Scope>						<gmd:level>							<gmd:MD_ScopeCode codeListValue="dataset" codeList="http://standards.iso.org/ittf/PubliclyAvailableStandards/ISO_19139_Schemas/resources/Codelist/ML_gmxCodelists.xml#MD_ScopeCode">dataset</gmd:MD_ScopeCode>						</gmd:level>					</gmd:DQ_Scope>				</gmd:scope>				<gmd:report>					<gmd:DQ_DomainConsistency>						<gmd:result>							<gmd:DQ_ConformanceResult>								<gmd:specification>									<gmd:CI_Citation>										<gmd:title>											<gco:CharacterString>Commission Regulation (EU) No 1089/2010 of 23 November 2010 implementing Directive 2007/2/EC of the European Parliament and of the Council as regards interoperability of spatial data sets and services</gco:CharacterString>										</gmd:title>										<gmd:date>											<gmd:CI_Date>												<gmd:date>													<gco:Date>2010-12-08</gco:Date>												</gmd:date>												<gmd:dateType>													<gmd:CI_DateTypeCode codeList="http://standards.iso.org/ittf/PubliclyAvailableStandards/ISO_19139_Schemas/resources/Codelist/ML_gmxCodelists.xml#CI_DateTypeCode" codeListValue="publication">publication</gmd:CI_DateTypeCode>												</gmd:dateType>											</gmd:CI_Date>										</gmd:date>									</gmd:CI_Citation>								</gmd:specification>								<gmd:explanation>									<gco:CharacterString>See the referenced specification</gco:CharacterString>								</gmd:explanation>								<gmd:pass>									<gco:Boolean>true</gco:Boolean>								</gmd:pass>							</gmd:DQ_ConformanceResult>						</gmd:result>					</gmd:DQ_DomainConsistency>				</gmd:report>				<gmd:lineage>					<gmd:LI_Lineage>						<gmd:statement>							<gco:CharacterString>Data supplied by Galway-Mayo Institute of Technology.</gco:CharacterString>						</gmd:statement>					</gmd:LI_Lineage>				</gmd:lineage>			</gmd:DQ_DataQuality>		  </gmd:dataQualityInfo></gmd:MD_Metadata>